Workbook

Sheet Budget
A1: DHL × UOB WonderLab 2026 — ฿5M Budget Model
A2: Edit yellow cells (Unit ฿ / Qty); subtotals & totals auto-calculate.
A4: Bucket | B4: Line item | C4: Unit ฿ | D4: Qty | E4: Subtotal ฿ | F4: Basis / source
A5: 1 · In-branch | B5: A1 posters | C5: 983 | D5: 108 | E5: =C5*D5 | F5: Gogoprint from ฿983
B6: Counter cards / tents | C6: 120 | D6: 360 | E6: =C6*D6 | F6: Gogoprint ~฿112 [est.]
B7: Box stickers (Green Stamp) | C7: 140 | D7: 1800 | E7: =C7*D7 | F7: Gogoprint holographic ฿140
B8: Branded standee | C8: 1500 | D8: 36 | E8: =C8*D8 | F8: Gogoprint standee [est.]
B9: Receipt redesign + thermal rolls | C9: 180000 | D9: 1 | E9: =C9*D9 | F9: thermal consumable [est.]
B10: In-branch screen content (creative) | C10: 250000 | D10: 1 | E10: =C10*D10 | F10: agency creative [est.]
B11: Install + refresh logistics (36 sites) | C11: 10000 | D11: 36 | E11: =C11*D11 | F11: rollout labour [est.]
A12: 2 · Digital | B12: QR landing + microsite | C12: 250000 | D12: 1 | E12: =C12*D12 | F12: agency dev [est.]
B13: LINE OA integration | C13: 350000 | D13: 1 | E13: =C13*D13 | F13: custom LINE dev [est.]
B14: LINE OA Pro subscription (3 mo) | C14: 1780 | D14: 3 | E14: =C14*D14 | F14: LINE OA Pro 2025
B15: LINE extra broadcast msgs | C15: 0.04 | D15: 3600000 | E15: =C15*D15 | F15: LINE ฿0.04/msg
B16: Thailand Green Map build | C16: 250000 | D16: 1 | E16: =C16*D16 | F16: data-viz [est.]
A17: 3 · Seller/SME | B17: Badge system + asset kit | C17: 200000 | D17: 1 | E17: =C17*D17 | F17: design+dev [est.]
B18: SME LINE-friend acquisition | C18: 15 | D18: 40000 | E18: =C18*D18 | F18: LINE friend ฿5–30, mid ฿15
B19: SME workshops/outreach | C19: 25000 | D19: 4 | E19: =C19*D19 | F19: events [est.]
A20: 4 · Content | B20: SME video shoot (days) | C20: 20000 | D20: 4 | E20: =C20*D20 | F20: Bangkok Video ฿20k/day
B21: Edit + multi-format versions | C21: 120000 | D21: 1 | E21: =C21*D21 | F21: post-production [est.]
B22: Crew/equip/location/music | C22: 150000 | D22: 1 | E22: =C22*D22 | F22: package inclusions
B23: Social content batch (3 mo) | C23: 50000 | D23: 3 | E23: =C23*D23 | F23: content retainer [est.]
B24: Paid amplification (light boost) | C24: 250000 | D24: 1 | E24: =C24*D24 | F24: LINE/Meta boost [est.]
A25: 5 · Measure/Staff | B25: Pre/post brand-lift survey (resp.) | C25: 700 | D25: 800 | E25: =C25*D25 | F25: CAPI/CAWI blend [est.], 2×400
B26: Staff briefing + scripts | C26: 40000 | D26: 1 | E26: =C26*D26 | F26: internal, low cost
A27: 6 · Contingency | B27: Buffer (reprints/variance/FX) | C27: 250000 | D27: 1 | E27: =C27*D27 | F27: 5% best practice
B28: GRAND TOTAL | E28: =SUM(E5:E27)
B30: Target cap | E30: 5000000
B31: Variance vs cap | E31: =E28-E30

Sheet Summary
A1: Budget by Bucket
A3: Bucket | B3: ฿ | C3: % of total
A4: 1 · In-branch | B4: =SUMIF(Budget!A:A,"1 · In-branch",Budget!E:E) | C4: =B4/B11
A5: 2 · Digital | B5: =SUMIF(Budget!A:A,"2 · Digital",Budget!E:E) | C5: =B5/B11
A6: 3 · Seller/SME | B6: =SUMIF(Budget!A:A,"3 · Seller/SME",Budget!E:E) | C6: =B6/B11
A7: 4 · Content | B7: =SUMIF(Budget!A:A,"4 · Content",Budget!E:E) | C7: =B7/B11
A8: 5 · Measure/Staff | B8: =SUMIF(Budget!A:A,"5 · Measure/Staff",Budget!E:E) | C8: =B8/B11
A9: 6 · Contingency | B9: =SUMIF(Budget!A:A,"6 · Contingency",Budget!E:E) | C9: =B9/B11
A11: TOTAL | B11: =SUM(B4:B10) | C11: 1

Sheet ROI Model
A1: ROI / Funnel Model (edit yellow)
A3: Campaign cost (฿) | B3: =Budget!E28 | C3: from Budget tab
A4: Customers reached (3 mo) | B4: 150000 | C4: proxy — DHL TH internal vol not public
A5: Awareness lift (pp) | B5: 0.2 | C5: pre/post survey; brand-lift 2× norm
A6: Opt-in conversion | B6: 0.1 | C6: proven eco-checkout 10–30%, use floor
A7: Incremental opt-ins | B7: =B4*B5*B6 | C7: reached × lift × opt-in
A8: Cost per aware customer (฿) | B8: =B3/(B4*B5) | C8: awareness efficiency
A9: Cost per incremental opt-in (฿) | B9: =B3/B7 | C9: falls as it scales
A10: Carbon cost to DHL (฿) | B10: 0 | C10: customers fund via GoGreen Plus
A12: Sensitivity — cost per opt-in at different opt-in rates
A13: Opt-in % | B13: Incremental opt-ins | C13: Cost / opt-in ฿
A14: 0.02 | B14: =$B$4*$B$5*A14 | C14: =$B$3/B14
A15: 0.05 | B15: =$B$4*$B$5*A15 | C15: =$B$3/B15
A16: 0.1 | B16: =$B$4*$B$5*A16 | C16: =$B$3/B16
A17: 0.2 | B17: =$B$4*$B$5*A17 | C17: =$B$3/B17
A18: 0.3 | B18: =$B$4*$B$5*A18 | C18: =$B$3/B18
